log_center_sdk/__init__.py
log_center_sdk/log_sender.py
log_center_sdk-0.1.dist-info/METADATA
log_center_sdk-0.1.dist-info/WHEEL
log_center_sdk-0.1.dist-info/top_level.txt
log_center_sdk-0.1.dist-info/RECORD
