Metadata-Version: 2.1
Name: log-center-sdk
Version: 0.1
Requires-Dist: httpx (>=0.24.0)
Requires-Dist: pydantic (>=2.0.0)
